wagtail_block_components/__init__.py
wagtail_block_components/apps.py
wagtail_block_components/registry.py
wagtail_block_components/templatetags/__init__.py
wagtail_block_components/templatetags/wagtail_block_components.py
wagtail_block_components-0.1.0.dist-info/licenses/LICENSE
wagtail_block_components-0.1.0.dist-info/METADATA
wagtail_block_components-0.1.0.dist-info/WHEEL
wagtail_block_components-0.1.0.dist-info/top_level.txt
wagtail_block_components-0.1.0.dist-info/RECORD
