Metadata-Version: 2.4
Name: wagtail-block-components
Version: 0.1.0
Summary: Use Wagtail blocks as reusable components in Django templates
Author-email: Joey Jurjens <joeyjurjens@gmail.com>
License: MIT
Project-URL: Homepage, https://github.com/joeyjurjens/wagtail-block-components
Project-URL: Repository, https://github.com/joeyjurjens/wagtail-block-components
Project-URL: Issues, https://github.com/joeyjurjens/wagtail-block-components/issues
Keywords: wagtail,django,components,blocks
Classifier: Development Status :: 3 - Alpha
Classifier: Environment :: Web Environment
Classifier: Framework :: Django
Classifier: Framework :: Wagtail
Classifier: Intended Audience :: Developers
Classifier: License :: OSI Approved :: MIT License
Classifier: Operating System :: OS Independent
Classifier: Programming Language :: Python :: 3
Classifier: Programming Language :: Python :: 3.8
Classifier: Programming Language :: Python :: 3.9
Classifier: Programming Language :: Python :: 3.10
Classifier: Programming Language :: Python :: 3.11
Classifier: Programming Language :: Python :: 3.12
Requires-Python: >=3.8
License-File: LICENSE
Requires-Dist: wagtail>=6.3
Provides-Extra: dev
Requires-Dist: ruff; extra == "dev"
Provides-Extra: test
Requires-Dist: pytest; extra == "test"
Requires-Dist: pytest-django; extra == "test"
Requires-Dist: pytest-cov; extra == "test"
Requires-Dist: Jinja2; extra == "test"
Dynamic: license-file
